LICENSE
MANIFEST.in
README.rst
requirements.txt
setup.py
sparkit_learn.egg-info/PKG-INFO
sparkit_learn.egg-info/SOURCES.txt
sparkit_learn.egg-info/dependency_links.txt
sparkit_learn.egg-info/pbr.json
sparkit_learn.egg-info/requires.txt
sparkit_learn.egg-info/top_level.txt
splearn/__init__.py
splearn/base.py
splearn/cross_validation.py
splearn/grid_search.py
splearn/naive_bayes.py
splearn/pipeline.py
splearn/rdd.py
splearn/cluster/__init__.py
splearn/cluster/dbscan.py
splearn/cluster/k_means_.py
splearn/cluster/tests/__init__.py
splearn/cluster/tests/test_k_means.py
splearn/decomposition/__init__.py
splearn/decomposition/truncated_svd.py
splearn/decomposition/tests/__init__.py
splearn/decomposition/tests/test_truncated_svd.py
splearn/feature_extraction/__init__.py
splearn/feature_extraction/dict_vectorizer.py
splearn/feature_extraction/text.py
splearn/feature_extraction/tests/__init__.py
splearn/feature_extraction/tests/test_dict_vectorizer.py
splearn/feature_extraction/tests/test_text.py
splearn/feature_selection/__init__.py
splearn/feature_selection/base.py
splearn/feature_selection/variance_threshold.py
splearn/feature_selection/tests/__init__.py
splearn/feature_selection/tests/test_variance_threshold.py
splearn/linear_model/__init__.py
splearn/linear_model/base.py
splearn/linear_model/logistic.py
splearn/linear_model/stochastic_gradient.py
splearn/linear_model/tests/__init__.py
splearn/linear_model/tests/test_base.py
splearn/linear_model/tests/test_logistic.py
splearn/linear_model/tests/test_stochastic_gradient.py
splearn/metrics/__init__.py
splearn/metrics/text.py
splearn/neighbors/__init__.py
splearn/neighbors/approximate.py
splearn/svm/__init__.py
splearn/svm/classes.py
splearn/svm/tests/__init__.py
splearn/svm/tests/test_classes.py
splearn/tests/__init__.py
splearn/tests/test_grid_search.py
splearn/tests/test_naive_bayes.py
splearn/tests/test_pipeline.py
splearn/tests/test_rdd.py
splearn/utils/__init__.py
splearn/utils/testing.py
splearn/utils/validation.py
splearn/utils/tests/__init__.py
splearn/utils/tests/test_utils.py