Metadata-Version: 1.0
Name: sparkit-learn
Version: 0.2.5
Summary: Scikit-learn on PySpark
Home-page: https://github.com/lensacom/sparkit-learn
Author: Krisztian Szucs, Andras Fulop
Author-email: krisztian.szucs@lensa.com, andras.fulop@lensa.com
License: Apache License, Version 2.0
Platform: UNKNOWN
